LICENSE
README.md
pyproject.toml
setup.py
bressen/__init__.py
bressen/basisgegevens.py
bressen/bressen.py
bressen/constants.py
bressen/exceptions.py
bressen/geometries.py
bressen/io.py
bressen/kering.py
bressen/styles.py
bressen/vlakken.py
bressen.egg-info/PKG-INFO
bressen.egg-info/SOURCES.txt
bressen.egg-info/dependency_links.txt
bressen.egg-info/requires.txt
bressen.egg-info/top_level.txt
bressen.egg-info/zip-safe
bressen/data/styles/bressen.qml
bressen/data/styles/bressen.sld
bressen/data/styles/bresvlakken.qml
bressen/data/styles/bresvlakken.sld
bressen/data/styles/keringen.qml
bressen/data/styles/keringen.sld
bressen/data/styles/peilvlakken.qml
bressen/data/styles/peilvlakken.sld
bressen/data/styles/watervlakken.qml
bressen/data/styles/watervlakken.sld
tests/test_basisgegevens.py
tests/test_bressen.py
tests/test_io.py