Metadata-Version: 2.1
Name: bressen
Version: 2024.5.0
Summary: Converteren van breslocaties naar bresvlakken
Author-email: Daniel Tollenaar <daniel@d2hydro.nl>
License: MIT
Project-URL: Source, https://github.com/d2hydro/bressen
Requires-Python: <3.13,>3.7
License-File: LICENSE
Requires-Dist: geopandas
Requires-Dist: pyogrio
Provides-Extra: tests
Requires-Dist: pytest; extra == "tests"
